preheat_open/__init__.py
preheat_open/_version.py
preheat_open/collection.py
preheat_open/configuration.py
preheat_open/conftest.py
preheat_open/interfaces.py
preheat_open/loadable_types.py
preheat_open/location.py
preheat_open/measurements.py
preheat_open/query.py
preheat_open/supplypoint.py
preheat_open/time.py
preheat_open/unit.py
preheat_open/zone.py
preheat_open/api/__init__.py
preheat_open/api/adapter.py
preheat_open/api/cache.py
preheat_open/api/conftest.py
preheat_open/api/control_setting_type.yaml
preheat_open/api/factories.py
preheat_open/api/mocks.py
preheat_open/api/session.py
preheat_open/api/types.py
preheat_open/api/test/__init__.py
preheat_open/api/test/test_adapter.py
preheat_open/api/test/test_cache.py
preheat_open/api/test/test_factories.py
preheat_open/api/test/test_mocks.py
preheat_open/api/test/test_session.py
preheat_open/api/test/test_types.py
preheat_open/api/test/mocks/configurations/config.yaml
preheat_open/api/test/mocks/configurations/config_anonymized.yaml
preheat_open/api/test/mocks/locations/1.yaml
preheat_open/test/__init__.py
preheat_open/test/test_collection.py
preheat_open/test/test_configuration.py
preheat_open/test/test_interfaces.py
preheat_open/test/test_location.py
preheat_open/test/test_measurements.py
preheat_open/test/test_query.py
preheat_open/test/test_setpoint_schedule.py
preheat_open/test/test_supplypoint.py
preheat_open/test/test_time.py
preheat_open/test/test_unit.py
preheat_open/test/test_zone.py
preheat_open-2.7.data/data/requirements/requirements.txt
preheat_open-2.7.dist-info/LICENSE
preheat_open-2.7.dist-info/METADATA
preheat_open-2.7.dist-info/WHEEL
preheat_open-2.7.dist-info/top_level.txt
preheat_open-2.7.dist-info/RECORD
