Metadata-Version: 2.1
Name: preheat-open
Version: 2.7
Summary: Python wrapper for Neogrid Technologies' REST API
Home-page: https://gitlab.com/neogrid-technologies-public/preheat-open-python
Author: Neogrid and contributors
Author-email: analytics@neogrid.dk
Project-URL: Bug Tracker, https://gitlab.com/neogrid-technologies-public/preheat-open-python/-/issues
Project-URL: Documentation, https://preheat-open.readthedocs.io/en/latest/
Project-URL: Source Code, https://gitlab.com/neogrid-technologies-public/preheat-open-python
Project-URL: Changelog, https://gitlab.com/neogrid-technologies-public/preheat-open-python/-/blob/master/RELEASE_NOTES.md
Requires-Python: >=3.10
License-File: LICENSE
Requires-Dist: requests
Requires-Dist: pandas >=2.0.0
Requires-Dist: numpy
Requires-Dist: pyyaml
Provides-Extra: dev
Requires-Dist: setuptools >=42 ; extra == 'dev'
Requires-Dist: wheel ; extra == 'dev'
Requires-Dist: pytest ; extra == 'dev'
Requires-Dist: pytest-cov ; extra == 'dev'
Requires-Dist: pytest-xdist ; extra == 'dev'
Requires-Dist: Sphinx <7.0.0 ; extra == 'dev'
Requires-Dist: m2r2 ; extra == 'dev'
Requires-Dist: sphinx-autodoc-typehints ; extra == 'dev'
Requires-Dist: sphinx-rtd-theme ; extra == 'dev'
Requires-Dist: nbsphinx ; extra == 'dev'
Requires-Dist: pandoc ; extra == 'dev'
Requires-Dist: lxml-html-clean ; extra == 'dev'
Provides-Extra: doc
Requires-Dist: Sphinx <7.0.0 ; extra == 'doc'
Requires-Dist: m2r2 ; extra == 'doc'
Requires-Dist: sphinx-autodoc-typehints ; extra == 'doc'
Requires-Dist: sphinx-rtd-theme ; extra == 'doc'
Requires-Dist: nbsphinx ; extra == 'doc'
Requires-Dist: pandoc ; extra == 'doc'
Requires-Dist: lxml-html-clean ; extra == 'doc'
